conv_opt/__init__.py
conv_opt/_version.py
conv_opt/core.py
conv_opt/solver/__init__.py
conv_opt/solver/cbc.py
conv_opt/solver/cplex.py
conv_opt/solver/cvxopt.py
conv_opt/solver/cvxpy.py
conv_opt/solver/cylp.py
conv_opt/solver/glpk.py
conv_opt/solver/gurobi.py
conv_opt/solver/minos.py
conv_opt/solver/mosek.py
conv_opt/solver/optlang.py
conv_opt/solver/quadprog.py
conv_opt/solver/scipy.py
conv_opt/solver/soplex.py
conv_opt/solver/xpress.py
conv_opt-0.0.13.dist-info/LICENSE
conv_opt-0.0.13.dist-info/METADATA
conv_opt-0.0.13.dist-info/WHEEL
conv_opt-0.0.13.dist-info/top_level.txt
conv_opt-0.0.13.dist-info/RECORD
