Metadata-Version: 2.1
Name: conv-opt
Version: 0.0.13
Summary: High-level Python package for solving linear and quadratic optimization problems using multiple solvers
Home-page: https://github.com/KarrLab/conv_opt
Author: Karr Lab
Author-email: info@karrlab.org
License: MIT
Download-URL: https://github.com/KarrLab/conv_opt
Keywords: convex optimization,linear programming,quadratic programming
Platform: UNKNOWN
Classifier: Development Status :: 3 - Alpha
Classifier: Intended Audience :: Science/Research
Classifier: License :: OSI Approved :: MIT License
Classifier: Programming Language :: Python
Classifier: Programming Language :: Python :: 2
Classifier: Programming Language :: Python :: 3
Classifier: Topic :: Scientific/Engineering :: Mathematics
Requires-Dist: abduct
Requires-Dist: attrdict
Requires-Dist: configobj
Requires-Dist: cython
Requires-Dist: mock
Requires-Dist: numpy
Requires-Dist: optlang
Requires-Dist: quadprog
Requires-Dist: scipy
Requires-Dist: swiglpk
Requires-Dist: sympy
Provides-Extra: all
Requires-Dist: capturer ; extra == 'all'
Requires-Dist: cplex ; extra == 'all'
Requires-Dist: cvxopt ; extra == 'all'
Requires-Dist: cvxpy (>=1.0.21) ; extra == 'all'
Requires-Dist: cylp (<=0.7.2) ; extra == 'all'
Requires-Dist: gurobipy ; extra == 'all'
Requires-Dist: mosek (>=8) ; extra == 'all'
Requires-Dist: qminospy ; extra == 'all'
Requires-Dist: soplex ; extra == 'all'
Requires-Dist: sphinx (>=1.8) ; extra == 'all'
Requires-Dist: sphinx-fontawesome ; extra == 'all'
Requires-Dist: sphinx-rtd-theme (>=0.4.2) ; extra == 'all'
Requires-Dist: sphinxcontrib-addmetahtml (>=0.1.1) ; extra == 'all'
Requires-Dist: sphinxcontrib-bibtex ; extra == 'all'
Requires-Dist: sphinxcontrib-googleanalytics (>=0.1.1) ; extra == 'all'
Requires-Dist: sphinxcontrib-spelling ; extra == 'all'
Requires-Dist: sphinxprettysearchresults ; extra == 'all'
Requires-Dist: xpress ; extra == 'all'
Provides-Extra: capture_output
Requires-Dist: capturer ; extra == 'capture_output'
Provides-Extra: cbc
Requires-Dist: cylp (<=0.7.2) ; extra == 'cbc'
Provides-Extra: cplex
Requires-Dist: cplex ; extra == 'cplex'
Provides-Extra: cvxopt
Requires-Dist: cvxopt ; extra == 'cvxopt'
Requires-Dist: cvxpy (>=1.0.21) ; extra == 'cvxopt'
Provides-Extra: cylp
Requires-Dist: cylp (<=0.7.2) ; extra == 'cylp'
Provides-Extra: docs
Requires-Dist: sphinx (>=1.8) ; extra == 'docs'
Requires-Dist: sphinx-fontawesome ; extra == 'docs'
Requires-Dist: sphinx-rtd-theme (>=0.4.2) ; extra == 'docs'
Requires-Dist: sphinxcontrib-addmetahtml (>=0.1.1) ; extra == 'docs'
Requires-Dist: sphinxcontrib-bibtex ; extra == 'docs'
Requires-Dist: sphinxcontrib-googleanalytics (>=0.1.1) ; extra == 'docs'
Requires-Dist: sphinxcontrib-spelling ; extra == 'docs'
Requires-Dist: sphinxprettysearchresults ; extra == 'docs'
Provides-Extra: gurobi
Requires-Dist: gurobipy ; extra == 'gurobi'
Provides-Extra: minos
Requires-Dist: qminospy ; extra == 'minos'
Provides-Extra: mosek
Requires-Dist: mosek (>=8) ; extra == 'mosek'
Provides-Extra: soplex
Requires-Dist: soplex ; extra == 'soplex'
Provides-Extra: tests
Requires-Dist: capturer ; extra == 'tests'
Provides-Extra: xpress
Requires-Dist: xpress ; extra == 'xpress'
